[
  {
    "kor": "다산의",
    "eng": "productive",
    "answer_count_kor": 1,
    "answer_count_eng": 1
  },
  {
    "kor": "단계",
    "eng": "phase",
    "answer_count_kor": 1,
    "answer_count_eng": 1
  },
  {
    "kor": "위기",
    "eng": "peril",
    "answer_count_kor": 1,
    "answer_count_eng": 1
  },
  {
    "kor": "부상을입히다",
    "eng": "wound",
    "answer_count_kor": 1,
    "answer_count_eng": 1
  },
  {
    "kor": "수의사",
    "eng": "veterinarian",
    "answer_count_kor": 1,
    "answer_count_eng": 1
  },
  {
    "kor": "반지름",
    "eng": "radius",
    "answer_count_kor": 1,
    "answer_count_eng": 1
  },
  {
    "kor": "하부조직구조",
    "eng": "infrastructure",
    "answer_count_kor": 1,
    "answer_count_eng": 1
  },
  {
    "kor": "잡종",
    "eng": "hybrid",
    "answer_count_kor": 1,
    "answer_count_eng": 1
  },
  {
    "kor": "원한",
    "eng": "grudge",
    "answer_count_kor": 1,
    "answer_count_eng": 1
  },
  {
    "kor": "쓰레기매립지",
    "eng": "landfill",
    "answer_count_kor": 1,
    "answer_count_eng": 1
  },
  {
    "kor": "굳어지다",
    "eng": "solidify",
    "answer_count_kor": 1,
    "answer_count_eng": 1
  },
  {
    "kor": "~하기쉬운",
    "eng": "liable",
    "answer_count_kor": 1,
    "answer_count_eng": 1
  },
  {
    "kor": "별개의",
    "eng": "discrete",
    "answer_count_kor": 1,
    "answer_count_eng": 1
  },
  {
    "kor": "불평하다",
    "eng": "grumble",
    "answer_count_kor": 1,
    "answer_count_eng": 1
  },
  {
    "kor": "열광",
    "eng": "enthusiasm",
    "answer_count_kor": 1,
    "answer_count_eng": 1
  },
  {
    "kor": "반격",
    "eng": "counterattack",
    "answer_count_kor": 1,
    "answer_count_eng": 1
  },
  {
    "kor": "번영하다",
    "eng": "prosper",
    "answer_count_kor": 1,
    "answer_count_eng": 1
  },
  {
    "kor": "무모한",
    "eng": "reckless",
    "answer_count_kor": 1,
    "answer_count_eng": 1
  },
  {
    "kor": "유괴",
    "eng": "kidnap",
    "answer_count_kor": 1,
    "answer_count_eng": 1
  },
  {
    "kor": "좌절",
    "eng": "setback",
    "answer_count_kor": 1,
    "answer_count_eng": 1
  },
  {
    "kor": "방해하다",
    "eng": "intrude",
    "answer_count_kor": 1,
    "answer_count_eng": 1
  },
  {
    "kor": "얽히게하다",
    "eng": "tangle",
    "answer_count_kor": 1,
    "answer_count_eng": 1
  },
  {
    "kor": "파산",
    "eng": "bankruptcy",
    "answer_count_kor": 1,
    "answer_count_eng": 1
  },
  {
    "kor": "알아내다",
    "eng": "uncover",
    "answer_count_kor": 1,
    "answer_count_eng": 1
  },
  {
    "kor": "합성의",
    "eng": "synthetic",
    "answer_count_kor": 1,
    "answer_count_eng": 1
  },
  {
    "kor": "위험",
    "eng": "pitfall",
    "answer_count_kor": 1,
    "answer_count_eng": 1
  },
  {
    "kor": "시작",
    "eng": "outset",
    "answer_count_kor": 1,
    "answer_count_eng": 1
  },
  {
    "kor": "유명한",
    "eng": "notable",
    "answer_count_kor": 1,
    "answer_count_eng": 1
  },
  {
    "kor": "빈틈없는",
    "eng": "prudent",
    "answer_count_kor": 1,
    "answer_count_eng": 1
  },
  {
    "kor": "초월하다",
    "eng": "transcend",
    "answer_count_kor": 1,
    "answer_count_eng": 1
  },
  {
    "kor": "두가지뜻으로해석가능한",
    "eng": "ambiguous",
    "answer_count_kor": 1,
    "answer_count_eng": 1
  },
  {
    "kor": "격노",
    "eng": "rage",
    "answer_count_kor": 1,
    "answer_count_eng": 1
  },
  {
    "kor": "꿰뚫다",
    "eng": "penetrate",
    "answer_count_kor": 1,
    "answer_count_eng": 1
  },
  {
    "kor": "비상식적인",
    "eng": "insane",
    "answer_count_kor": 1,
    "answer_count_eng": 1
  },
  {
    "kor": "사지",
    "eng": "limb",
    "answer_count_kor": 1,
    "answer_count_eng": 1
  },
  {
    "kor": "누적되는",
    "eng": "cumulative",
    "answer_count_kor": 1,
    "answer_count_eng": 1
  },
  {
    "kor": "변동",
    "eng": "fluctuation",
    "answer_count_kor": 1,
    "answer_count_eng": 1
  },
  {
    "kor": "보조금",
    "eng": "subsidy",
    "answer_count_kor": 1,
    "answer_count_eng": 1
  },
  {
    "kor": "조사",
    "eng": "scrutiny",
    "answer_count_kor": 1,
    "answer_count_eng": 1
  },
  {
    "kor": "수분",
    "eng": "pollination",
    "answer_count_kor": 1,
    "answer_count_eng": 1
  }
]