[
  {
    "kor": "도장",
    "eng": "seal",
    "answer_count_kor": 1,
    "answer_count_eng": 1
  },
  {
    "kor": "나타나다",
    "eng": "appear",
    "answer_count_kor": 1,
    "answer_count_eng": 1
  },
  {
    "kor": "대리점",
    "eng": "agency",
    "answer_count_kor": 1,
    "answer_count_eng": 1
  },
  {
    "kor": "연설하다",
    "eng": "address",
    "answer_count_kor": 1,
    "answer_count_eng": 1
  },
  {
    "kor": "겸손한",
    "eng": "modest",
    "answer_count_kor": 1,
    "answer_count_eng": 1
  },
  {
    "kor": "비교하다",
    "eng": "compare",
    "answer_count_kor": 1,
    "answer_count_eng": 1
  },
  {
    "kor": "내부의",
    "eng": "inner",
    "answer_count_kor": 1,
    "answer_count_eng": 1
  },
  {
    "kor": "영수증",
    "eng": "receipt",
    "answer_count_kor": 1,
    "answer_count_eng": 1
  },
  {
    "kor": "쪼개다",
    "eng": "split",
    "answer_count_kor": 1,
    "answer_count_eng": 1
  },
  {
    "kor": "계약하다",
    "eng": "contract",
    "answer_count_kor": 1,
    "answer_count_eng": 1
  },
  {
    "kor": "기재하다",
    "eng": "register",
    "answer_count_kor": 1,
    "answer_count_eng": 1
  },
  {
    "kor": "극복하다",
    "eng": "conquer",
    "answer_count_kor": 1,
    "answer_count_eng": 1
  },
  {
    "kor": "가상의",
    "eng": "virtual",
    "answer_count_kor": 1,
    "answer_count_eng": 1
  },
  {
    "kor": "공격하다",
    "eng": "attack",
    "answer_count_kor": 1,
    "answer_count_eng": 1
  },
  {
    "kor": "그럼에도불구하고",
    "eng": "nevertheless",
    "answer_count_kor": 1,
    "answer_count_eng": 1
  },
  {
    "kor": "등록하다",
    "eng": "enroll",
    "answer_count_kor": 1,
    "answer_count_eng": 1
  },
  {
    "kor": "감독하다",
    "eng": "supervise",
    "answer_count_kor": 1,
    "answer_count_eng": 1
  },
  {
    "kor": "영양",
    "eng": "nutrition",
    "answer_count_kor": 1,
    "answer_count_eng": 1
  },
  {
    "kor": "성직자",
    "eng": "priest",
    "answer_count_kor": 1,
    "answer_count_eng": 1
  },
  {
    "kor": "강요하다",
    "eng": "impose",
    "answer_count_kor": 1,
    "answer_count_eng": 1
  },
  {
    "kor": "토론",
    "eng": "debate",
    "answer_count_kor": 1,
    "answer_count_eng": 1
  },
  {
    "kor": "반대의",
    "eng": "contrary",
    "answer_count_kor": 1,
    "answer_count_eng": 1
  },
  {
    "kor": "발생하다",
    "eng": "arise",
    "answer_count_kor": 1,
    "answer_count_eng": 1
  },
  {
    "kor": "특성",
    "eng": "trait",
    "answer_count_kor": 1,
    "answer_count_eng": 1
  },
  {
    "kor": "탐욕",
    "eng": "greed",
    "answer_count_kor": 1,
    "answer_count_eng": 1
  },
  {
    "kor": "보증하다",
    "eng": "ensure",
    "answer_count_kor": 1,
    "answer_count_eng": 1
  },
  {
    "kor": "가혹한",
    "eng": "harsh",
    "answer_count_kor": 1,
    "answer_count_eng": 1
  },
  {
    "kor": "소매",
    "eng": "retail",
    "answer_count_kor": 1,
    "answer_count_eng": 1
  },
  {
    "kor": "고상한",
    "eng": "elegant",
    "answer_count_kor": 1,
    "answer_count_eng": 1
  },
  {
    "kor": "결점",
    "eng": "defect",
    "answer_count_kor": 1,
    "answer_count_eng": 1
  },
  {
    "kor": "통근",
    "eng": "commute",
    "answer_count_kor": 1,
    "answer_count_eng": 1
  },
  {
    "kor": "대작",
    "eng": "masterpiece",
    "answer_count_kor": 1,
    "answer_count_eng": 1
  },
  {
    "kor": "대변동",
    "eng": "earthquake",
    "answer_count_kor": 1,
    "answer_count_eng": 1
  },
  {
    "kor": "가뭄",
    "eng": "drought",
    "answer_count_kor": 1,
    "answer_count_eng": 1
  },
  {
    "kor": "놀라운",
    "eng": "extraordinary",
    "answer_count_kor": 1,
    "answer_count_eng": 1
  },
  {
    "kor": "거주하다",
    "eng": "inhabit",
    "answer_count_kor": 1,
    "answer_count_eng": 1
  },
  {
    "kor": "버리다",
    "eng": "abandon",
    "answer_count_kor": 1,
    "answer_count_eng": 1
  },
  {
    "kor": "기준",
    "eng": "criteria",
    "answer_count_kor": 1,
    "answer_count_eng": 1
  },
  {
    "kor": "교육",
    "eng": "nurture",
    "answer_count_kor": 1,
    "answer_count_eng": 1
  },
  {
    "kor": "선입관",
    "eng": "prejudice",
    "answer_count_kor": 1,
    "answer_count_eng": 1
  }
]