[
  {
    "kor": "(구성) 요소",
    "eng": "component",
    "answer_count_kor": 1,
    "answer_count_eng": 1
  },
  {
    "kor": "구분분리하다",
    "eng": "segregate",
    "answer_count_kor": 1,
    "answer_count_eng": 1
  },
  {
    "kor": "사소한",
    "eng": "trivial",
    "answer_count_kor": 1,
    "answer_count_eng": 1
  },
  {
    "kor": "경치가 좋은",
    "eng": "scenic",
    "answer_count_kor": 1,
    "answer_count_eng": 1
  },
  {
    "kor": "구기다구겨지다",
    "eng": "crumple",
    "answer_count_kor": 1,
    "answer_count_eng": 1
  },
  {
    "kor": "척추가 있는",
    "eng": "vertebrate",
    "answer_count_kor": 1,
    "answer_count_eng": 1
  },
  {
    "kor": "의회",
    "eng": "council",
    "answer_count_kor": 1,
    "answer_count_eng": 1
  },
  {
    "kor": "약속",
    "eng": "pledge",
    "answer_count_kor": 1,
    "answer_count_eng": 1
  },
  {
    "kor": "(총)인원",
    "eng": "personnel",
    "answer_count_kor": 1,
    "answer_count_eng": 1
  },
  {
    "kor": "사회 복귀",
    "eng": "rehabilitation",
    "answer_count_kor": 1,
    "answer_count_eng": 1
  },
  {
    "kor": "불가분한",
    "eng": "inseparable",
    "answer_count_kor": 1,
    "answer_count_eng": 1
  },
  {
    "kor": "피하다",
    "eng": "evade",
    "answer_count_kor": 1,
    "answer_count_eng": 1
  },
  {
    "kor": "제재",
    "eng": "sanction",
    "answer_count_kor": 1,
    "answer_count_eng": 1
  },
  {
    "kor": "폭행(죄)",
    "eng": "assault",
    "answer_count_kor": 1,
    "answer_count_eng": 1
  },
  {
    "kor": "(배",
    "eng": "embark",
    "answer_count_kor": 1,
    "answer_count_eng": 1
  },
  {
    "kor": "창고",
    "eng": "warehouse",
    "answer_count_kor": 1,
    "answer_count_eng": 1
  },
  {
    "kor": "암시암묵적인",
    "eng": "implicit",
    "answer_count_kor": 1,
    "answer_count_eng": 1
  },
  {
    "kor": "시들다",
    "eng": "wither",
    "answer_count_kor": 1,
    "answer_count_eng": 1
  },
  {
    "kor": "자극",
    "eng": "incentive",
    "answer_count_kor": 1,
    "answer_count_eng": 1
  },
  {
    "kor": "(거울 등에 비친) 상모습",
    "eng": "reflection",
    "answer_count_kor": 1,
    "answer_count_eng": 1
  },
  {
    "kor": "투명한",
    "eng": "transparent",
    "answer_count_kor": 1,
    "answer_count_eng": 1
  },
  {
    "kor": "생활 편의 시설",
    "eng": "amenity",
    "answer_count_kor": 1,
    "answer_count_eng": 1
  },
  {
    "kor": "재생재현하다",
    "eng": "reproduce",
    "answer_count_kor": 1,
    "answer_count_eng": 1
  },
  {
    "kor": "공간의",
    "eng": "spatial",
    "answer_count_kor": 1,
    "answer_count_eng": 1
  },
  {
    "kor": "관개",
    "eng": "irrigation",
    "answer_count_kor": 1,
    "answer_count_eng": 1
  },
  {
    "kor": "포괄적인",
    "eng": "generic",
    "answer_count_kor": 1,
    "answer_count_eng": 1
  },
  {
    "kor": "전적인",
    "eng": "utter",
    "answer_count_kor": 1,
    "answer_count_eng": 1
  },
  {
    "kor": "글로 옮긴 것",
    "eng": "transcript",
    "answer_count_kor": 1,
    "answer_count_eng": 1
  },
  {
    "kor": "~을 위한 기반을 마련하다",
    "eng": "set the stage for",
    "answer_count_kor": 1,
    "answer_count_eng": 1
  },
  {
    "kor": "~와 밀접한 관련이 있다",
    "eng": "be bound up with",
    "answer_count_kor": 1,
    "answer_count_eng": 1
  }
]