[
  {
    "kor": "묶다",
    "eng": "tie",
    "answer_count_kor": 1,
    "answer_count_eng": 1
  },
  {
    "kor": "냄새가 나다",
    "eng": "smell",
    "answer_count_kor": 1,
    "answer_count_eng": 1
  },
  {
    "kor": "떠나다; 남겨두다",
    "eng": "leave",
    "answer_count_kor": 1,
    "answer_count_eng": 1
  },
  {
    "kor": "변하다",
    "eng": "change",
    "answer_count_kor": 1,
    "answer_count_eng": 1
  },
  {
    "kor": "(스포츠",
    "eng": "fan",
    "answer_count_kor": 1,
    "answer_count_eng": 1
  },
  {
    "kor": "포스터",
    "eng": "poster",
    "answer_count_kor": 1,
    "answer_count_eng": 1
  },
  {
    "kor": "틀린",
    "eng": "wrong",
    "answer_count_kor": 1,
    "answer_count_eng": 1
  },
  {
    "kor": "~을 가로질러; ~ 맞은편에",
    "eng": "across",
    "answer_count_kor": 1,
    "answer_count_eng": 1
  },
  {
    "kor": "자원봉사자; 자원하다",
    "eng": "volunteer",
    "answer_count_kor": 1,
    "answer_count_eng": 1
  },
  {
    "kor": "종류",
    "eng": "type",
    "answer_count_kor": 1,
    "answer_count_eng": 1
  },
  {
    "kor": "훌륭한",
    "eng": "great",
    "answer_count_kor": 1,
    "answer_count_eng": 1
  },
  {
    "kor": "같이",
    "eng": "together",
    "answer_count_kor": 1,
    "answer_count_eng": 1
  },
  {
    "kor": "들다",
    "eng": "hold",
    "answer_count_kor": 1,
    "answer_count_eng": 1
  },
  {
    "kor": "출구",
    "eng": "exit",
    "answer_count_kor": 1,
    "answer_count_eng": 1
  },
  {
    "kor": "가장 좋아하는",
    "eng": "favorite",
    "answer_count_kor": 1,
    "answer_count_eng": 1
  },
  {
    "kor": "속도",
    "eng": "speed",
    "answer_count_kor": 1,
    "answer_count_eng": 1
  },
  {
    "kor": "것",
    "eng": "thing",
    "answer_count_kor": 1,
    "answer_count_eng": 1
  },
  {
    "kor": "단계",
    "eng": "stage",
    "answer_count_kor": 1,
    "answer_count_eng": 1
  },
  {
    "kor": "~에 도착하다",
    "eng": "get to",
    "answer_count_kor": 1,
    "answer_count_eng": 1
  },
  {
    "kor": "곧바로",
    "eng": "right away",
    "answer_count_kor": 1,
    "answer_count_eng": 1
  }
]