[
  {
    "kor": "인공의",
    "eng": "artificial",
    "answer_count_kor": 1,
    "answer_count_eng": 1
  },
  {
    "kor": "장인",
    "eng": "artisan",
    "answer_count_kor": 1,
    "answer_count_eng": 1
  },
  {
    "kor": "예술가",
    "eng": "artist",
    "answer_count_kor": 1,
    "answer_count_eng": 1
  },
  {
    "kor": "(뜻밖의) 재난",
    "eng": "disaster",
    "answer_count_kor": 1,
    "answer_count_eng": 1
  },
  {
    "kor": "우주 비행사",
    "eng": "astronaut",
    "answer_count_kor": 1,
    "answer_count_eng": 1
  },
  {
    "kor": "천문학",
    "eng": "astronomy",
    "answer_count_kor": 1,
    "answer_count_eng": 1
  },
  {
    "kor": "점성학",
    "eng": "astrology",
    "answer_count_kor": 1,
    "answer_count_eng": 1
  },
  {
    "kor": "(곰곰이) 생각하다",
    "eng": "consider",
    "answer_count_kor": 1,
    "answer_count_eng": 1
  },
  {
    "kor": "청중",
    "eng": "audience",
    "answer_count_kor": 1,
    "answer_count_eng": 1
  },
  {
    "kor": "(~에) 복종하다",
    "eng": "obey",
    "answer_count_kor": 1,
    "answer_count_eng": 1
  },
  {
    "kor": "붕대(를 감다)",
    "eng": "bandage",
    "answer_count_kor": 1,
    "answer_count_eng": 1
  },
  {
    "kor": "결속",
    "eng": "bond",
    "answer_count_kor": 1,
    "answer_count_eng": 1
  },
  {
    "kor": "다발",
    "eng": "bundle",
    "answer_count_kor": 1,
    "answer_count_eng": 1
  },
  {
    "kor": "묶다; 결속시키다; 속박제한하다",
    "eng": "bind",
    "answer_count_kor": 1,
    "answer_count_eng": 1
  },
  {
    "kor": "주점; 막대",
    "eng": "bar",
    "answer_count_kor": 1,
    "answer_count_eng": 1
  },
  {
    "kor": "울타리; 장애물",
    "eng": "barrier",
    "answer_count_kor": 1,
    "answer_count_eng": 1
  },
  {
    "kor": "당황하게 하다",
    "eng": "embarrass",
    "answer_count_kor": 1,
    "answer_count_eng": 1
  },
  {
    "kor": "전기",
    "eng": "biography",
    "answer_count_kor": 1,
    "answer_count_eng": 1
  },
  {
    "kor": "생물학",
    "eng": "biology",
    "answer_count_kor": 1,
    "answer_count_eng": 1
  }
]