[
  {
    "kor": "(물리적) 접촉; 연락; 연락하다",
    "eng": "contact",
    "answer_count_kor": 1,
    "answer_count_eng": 1
  },
  {
    "kor": "허락허가하다; 허가(증)",
    "eng": "permit",
    "answer_count_kor": 1,
    "answer_count_eng": 1
  },
  {
    "kor": "석방해방하다; 놓아주다; 공개발표하다",
    "eng": "release",
    "answer_count_kor": 1,
    "answer_count_eng": 1
  },
  {
    "kor": "제안하다; 청혼하다",
    "eng": "propose",
    "answer_count_kor": 1,
    "answer_count_eng": 1
  },
  {
    "kor": "애쓰다",
    "eng": "struggle",
    "answer_count_kor": 1,
    "answer_count_eng": 1
  },
  {
    "kor": "특징",
    "eng": "characteristic",
    "answer_count_kor": 1,
    "answer_count_eng": 1
  },
  {
    "kor": "(병 등에) 시달리다; 고통 받다; (불쾌한 일을) 겪다당하다",
    "eng": "suffer",
    "answer_count_kor": 1,
    "answer_count_eng": 1
  },
  {
    "kor": "운명",
    "eng": "fate",
    "answer_count_kor": 1,
    "answer_count_eng": 1
  },
  {
    "kor": "귀중한",
    "eng": "precious",
    "answer_count_kor": 1,
    "answer_count_eng": 1
  },
  {
    "kor": "동일한",
    "eng": "equal",
    "answer_count_kor": 1,
    "answer_count_eng": 1
  },
  {
    "kor": "도시의",
    "eng": "urban",
    "answer_count_kor": 1,
    "answer_count_eng": 1
  },
  {
    "kor": "비추다; 반사하다; 반영하다",
    "eng": "reflect",
    "answer_count_kor": 1,
    "answer_count_eng": 1
  },
  {
    "kor": "알고 있는 ; 의식이 있는",
    "eng": "conscious",
    "answer_count_kor": 1,
    "answer_count_eng": 1
  },
  {
    "kor": "괴롭히다",
    "eng": "bother",
    "answer_count_kor": 1,
    "answer_count_eng": 1
  },
  {
    "kor": "일반적으로; 대개",
    "eng": "generally",
    "answer_count_kor": 1,
    "answer_count_eng": 1
  },
  {
    "kor": "청소하다",
    "eng": "sweep",
    "answer_count_kor": 1,
    "answer_count_eng": 1
  },
  {
    "kor": "위반하다",
    "eng": "violate",
    "answer_count_kor": 1,
    "answer_count_eng": 1
  },
  {
    "kor": "소유소지하다",
    "eng": "possess",
    "answer_count_kor": 1,
    "answer_count_eng": 1
  },
  {
    "kor": "균형이 잡혀",
    "eng": "in balance",
    "answer_count_kor": 1,
    "answer_count_eng": 1
  },
  {
    "kor": "될 수 있는 대로",
    "eng": "as ~ as possible",
    "answer_count_kor": 1,
    "answer_count_eng": 1
  }
]